PyTurboGen/__init__.py
PyTurboGen/main.py
pyturbogen-1.0.0.dist-info/LICENSE
pyturbogen-1.0.0.dist-info/METADATA
pyturbogen-1.0.0.dist-info/WHEEL
pyturbogen-1.0.0.dist-info/top_level.txt
pyturbogen-1.0.0.dist-info/RECORD
