Metadata-Version: 2.1
Name: pyturbogen
Version: 1.0.0
Summary: A simple image generation library in Python that uses the Turbo model
Home-page: https://github.com/Coder-Gaurav997/pyturbogen
Author: Gaurav Pandey
Author-email: Gaurav Pandey <golupandey95207@gmail.com>
License: MIT License
Project-URL: Homepage, https://github.com/Coder-Gaurav997/pyturbogen
Project-URL: Bug Tracker, https://github.com/Coder-Gaurav997/pyturbogen/issues
Classifier: Programming Language :: Python :: 3
Classifier: License :: OSI Approved :: MIT License
Classifier: Operating System :: OS Independent
Requires-Python: >=3.7
License-File: LICENSE
